jsonrouter/__init__.py
jsonrouter/__version__.py
jsonrouter/core.py
jsonrouter/routers/__init__.py
jsonrouter/routers/grafana.py
jsonrouter/routers/pagerduty.py
jsonrouter/routers/slack.py
jsonrouter-0.4.9.dist-info/LICENSE
jsonrouter-0.4.9.dist-info/METADATA
jsonrouter-0.4.9.dist-info/WHEEL
jsonrouter-0.4.9.dist-info/top_level.txt
jsonrouter-0.4.9.dist-info/RECORD
