Metadata-Version: 2.1
Name: jsonrouter
Version: 0.4.9
Summary: JSON based events router, inspired from an AWS Lambda project.
Home-page: https://github.com/srhopkins/jsonrouter
Author: Steven Hopkins
Author-email: steve@hopkins.rocks
License: MIT
Platform: UNKNOWN
Classifier: License :: OSI Approved :: MIT License
Classifier: Programming Language :: Python
Classifier: Programming Language :: Python :: 3
Classifier: Programming Language :: Python :: 3.5
Classifier: Programming Language :: Python :: Implementation :: CPython
Classifier: Programming Language :: Python :: Implementation :: PyPy
Requires-Python: >=3.5.0
Requires-Dist: pyyaml
Requires-Dist: jsonpath-rw (>=1.4.0)
